prologue/__init__.py
prologue/block.py
prologue/common.py
prologue/context.py
prologue/registry.py
prologue/directives/__init__.py
prologue/directives/base.py
prologue/directives/common.py
prologue/directives/conditional.py
prologue/directives/define.py
prologue/directives/for_loop.py
prologue/directives/include.py
prologue/directives/message.py
prologue-1.2.data/data/LICENSE
prologue-1.2.dist-info/LICENSE
prologue-1.2.dist-info/METADATA
prologue-1.2.dist-info/WHEEL
prologue-1.2.dist-info/top_level.txt
prologue-1.2.dist-info/RECORD
