Metadata-Version: 2.1
Name: prologue
Version: 1.2
Summary: General purpose preprocessor written in Python
Home-page: https://github.com/Intuity
Author: Peter Birch
License: Apache License, Version 2.0
Project-URL: Source, https://github.com/Intuity/prologue
Platform: UNKNOWN
Requires-Python: >=3.6.10
Requires-Dist: asteval
Requires-Dist: astunparse
